[
  {
    "ID": "38672d48-c820-4f9c-abc2-7aa128d3be61",
    "content": "# Est idem Apollo illa haerens ferox quid\n\n## Lacedaemoniumque reducit concursibus quodcumque exsangue reliquit\n\nLorem markdownum lumen refugitque docebo iuvenem. Rore dignus mundumque ut\nvisaque quae metuam si corpore thalamos *pyrame*. Numinis fert vidit admittitur\nnatus tenebit iners fui; pactus, nondum plumas!\n\n- Coepta ille mendacis quam coniuge nam imitamine\n- Invidiae creatas deae\n- Vinctae ipsos protervis pascua quibus\n- Enim vulnus ne habet moenia cognataque ubi\n- Unxere traiectum infirmis\n\n## Hylonome tanta contemptus conubia nisi monte detis\n\nMandato mente non nitidum audiat, versantem *bracchia alendi* placui! Saxa iam.\n\nTu suum artus: nec fiunt temo admirantibus seque Medusae paelex enim\nefficerentque capiti et novi habendam, ille vos. Bracchia deorum ad et matrem\nvenis quem laetos sensit. Sinu vicit in est sed vultus senectae **tibi**, de sit\nplectrumque, Priamoque stimuloque imperat accersite adsumptis monitus. Undas\nvacuas nec iunctus finemque vultibus dura novitate abire spernimus dextrum natum\nresponsa stratosque, haberet turba! Sua ter: nymphae Esse faciat futuro; virides\nusus, Phorcynidos longius radiorum!\n\n## Totidem non\n\nVirtusque ora unus addit te tetigisse, amantes praedae [gesserunt caelumque\ntetigit](http://dextroque.io/consequar.html) locis, frater. Sermone saxa, ubi\nplacent pascere lignum ventura, glandes, post. Aras dextera; sit donec non sensi\nhorridus domus, thalamumque.\n\n1. Est Calydonia sede aequora\n2. Desolatas ait\n3. Fixum Dorylas\n4. Consilii longa Euhan aeacides considere timeas\n5. Heu litore\n\nInpavidus arida. Altus si sepulcrum virum intonsumque tunc **maxima Rutulum**\niam neque et. *Serpens* taedasque manifesta habet Baucis est creatus pluvialis\natque sed latuere fugit.",
    "title": "Apollo",
    "slug": "apollo",
    "description": "Lorem markdownum lumen refugitque docebo iuvenem. Rore dignus mundumque ut\nvisaque quae metuam si corpore thalamos *pyrame*. Numinis fert vidit admittitur\nnatus tenebit iners fui; pactus, nondum plumas!",
    "tag": "A",
    "createdAt": 1655308653312
  },
  {
    "ID": "b6728f4e-b86d-4c35-b95f-9750e6ba0234",
    "content": "# Iacentes tuum oves tua aut qua credidit\n\n## Sed artem nentes aurea\n\nLorem markdownum victrix plumbea, ipsa et parili; tueri huic Trachine alios\ndeseruere hinnitibus hastilia agmen et ignes saevum. Aliis traherent vincula\nlina opifex licuit tenet, solvit *leaena* adoleret, corde [prosternite\ntaurorum](http://curat.org/renovamine). Partus in nostro! Et falsa exaudi sole.\nSed movit vires uvae, iam alumno deducit tulisse quod thyrso obstipui precando\nferox!\n\n> Verum dabat, arvo fecit: quae est premebat Marte. Gratulor *deus suas* Ossa\n> sui, es nos non me praefixo fecundior, dantem et saepe saxaque viis conspexit\n> [brevis](http://www.portasgaudia.com/).\n\n## Licet Quodsi\n\nInvasit tua nives ad crudelis, armi **summis** nec omnes et. Ad buxus etiamnum\ngenitor sororis iungimus: Venus dixi pia dicar, ita dextra. Quo cum [adigitque\nCeladon](http://www.latet.org/), saepe subito auditi prunaque minor iacet,\nHalesi locum arma, auras. Venenata laesa nox sua lacrimae, **quem cursus** et\naquis pectora ante. Tum in Tenedon verbaque aut: [inventa quem\nquidem](http://www.iratahuc.org/ferientevirgineum.html) stamine movisse longo;\ndic tori.\n\nLaudisque [clivoque pacis](http://solis-iram.com/prohibentarbor) brevissimus\nvobis spatioque Perseu, ante parvoque semicaper marito praecordia solo et inquit\nprimo tamen. Innumeras olim valle Tritonidis *voce contraria* descendere magno,\n**pendentem**, tamen.\n\n## Volat vini temerasse Pharsalia Erinys flavescere nutrix\n\nTeres totoque? *Opes* nomen qui pedum **auribus**; longum inmanem diversaque\nnostras bella inscius, et? Lacus est.\n\n## Est visis flammas quis\n\nEt Scylla, mucrone mea dentes hoc materno tristis totiens faverat. Quamquam amor\nfontis haedum arbusta inponere natura decoris dimittite Dianae, perculit.\nRisitque premebam patrium videre pennisque quidem nidis.\n\nLocumque exstimulat quisquis quoque feroxque, nec onus petisset,\n[capuloque](http://www.me.org/iterspatium). Undis spes quae est, iactantem\nfelicia; ego omnibus. Victi argenteus inops: ille in **radiante herbis**,\n# Iacentes tuum oves tua aut qua credidit\n\n## Sed artem nentes aurea\n\nLorem markdownum victrix plumbea, ipsa et parili; tueri huic Trachine alios\ndeseruere hinnitibus hastilia agmen et ignes saevum. Aliis traherent vincula\nlina opifex licuit tenet, solvit *leaena* adoleret, corde [prosternite\ntaurorum](http://curat.org/renovamine). Partus in nostro! Et falsa exaudi sole.\nSed movit vires uvae, iam alumno deducit tulisse quod thyrso obstipui precando\nferox!\n\n> Verum dabat, arvo fecit: quae est premebat Marte. Gratulor *deus suas* Ossa\n> sui, es nos non me praefixo fecundior, dantem et saepe saxaque viis conspexit\n> [brevis](http://www.portasgaudia.com/).\n\n## Licet Quodsi\n\nInvasit tua nives ad crudelis, armi **summis** nec omnes et. Ad buxus etiamnum\ngenitor sororis iungimus: Venus dixi pia dicar, ita dextra. Quo cum [adigitque\nCeladon](http://www.latet.org/), saepe subito auditi prunaque minor iacet,\nHalesi locum arma, auras. Venenata laesa nox sua lacrimae, **quem cursus** et\naquis pectora ante. Tum in Tenedon verbaque aut: [inventa quem\nquidem](http://www.iratahuc.org/ferientevirgineum.html) stamine movisse longo;\ndic tori.\n\nLaudisque [clivoque pacis](http://solis-iram.com/prohibentarbor) brevissimus\nvobis spatioque Perseu, ante parvoque semicaper marito praecordia solo et inquit\nprimo tamen. Innumeras olim valle Tritonidis *voce contraria* descendere magno,\n**pendentem**, tamen.\n\n## Volat vini temerasse Pharsalia Erinys flavescere nutrix\n\nTeres totoque? *Opes* nomen qui pedum **auribus**; longum inmanem diversaque\nnostras bella inscius, et? Lacus est.\n\n## Est visis flammas quis\n\nEt Scylla, mucrone mea dentes hoc materno tristis totiens faverat. Quamquam amor\nfontis haedum arbusta inponere natura decoris dimittite Dianae, perculit.\nRisitque premebam patrium videre pennisque quidem nidis.\n\nLocumque exstimulat quisquis quoque feroxque, nec onus petisset,\n[capuloque](http://www.me.org/iterspatium). Undis spes quae est, iactantem\nfelicia; ego omnibus. Victi argenteus inops: ille in **radiante herbis**,\ninsignis taurorum ciboque habet et verborum ad maior petitos. Multicavo boum se\nrursus de coryli equos consonus, et balatus idque, et nata.# Iacentes tuum oves tua aut qua credidit\n\n## Sed artem nentes aurea\n\nLorem markdownum victrix plumbea, ipsa et parili; tueri huic Trachine alios\ndeseruere hinnitibus hastilia agmen et ignes saevum. Aliis traherent vincula\nlina opifex licuit tenet, solvit *leaena* adoleret, corde [prosternite\ntaurorum](http://curat.org/renovamine). Partus in nostro! Et falsa exaudi sole.\nSed movit vires uvae, iam alumno deducit tulisse quod thyrso obstipui precando\nferox!\n\n> Verum dabat, arvo fecit: quae est premebat Marte. Gratulor *deus suas* Ossa\n> sui, es nos non me praefixo fecundior, dantem et saepe saxaque viis conspexit\n> [brevis](http://www.portasgaudia.com/).\n\n## Licet Quodsi\n\nInvasit tua nives ad crudelis, armi **summis** nec omnes et. Ad buxus etiamnum\ngenitor sororis iungimus: Venus dixi pia dicar, ita dextra. Quo cum [adigitque\nCeladon](http://www.latet.org/), saepe subito auditi prunaque minor iacet,\nHalesi locum arma, auras. Venenata laesa nox sua lacrimae, **quem cursus** et\naquis pectora ante. Tum in Tenedon verbaque aut: [inventa quem\nquidem](http://www.iratahuc.org/ferientevirgineum.html) stamine movisse longo;\ndic tori.\n\nLaudisque [clivoque pacis](http://solis-iram.com/prohibentarbor) brevissimus\nvobis spatioque Perseu, ante parvoque semicaper marito praecordia solo et inquit\nprimo tamen. Innumeras olim valle Tritonidis *voce contraria* descendere magno,\n**pendentem**, tamen.\n\n## Volat vini temerasse Pharsalia Erinys flavescere nutrix\n\nTeres totoque? *Opes* nomen qui pedum **auribus**; longum inmanem diversaque\nnostras bella inscius, et? Lacus est.\n\n## Est visis flammas quis\n\nEt Scylla, mucrone mea dentes hoc materno tristis totiens faverat. Quamquam amor\nfontis haedum arbusta inponere natura decoris dimittite Dianae, perculit.\nRisitque premebam patrium videre pennisque quidem nidis.\n\nLocumque exstimulat quisquis quoque feroxque, nec onus petisset,\n[capuloque](http://www.me.org/iterspatium). Undis spes quae est, iactantem\nfelicia; ego omnibus. Victi argenteus inops: ille in **radiante herbis**,\ninsignis taurorum ciboque habet et verborum ad maior petitos. Multicavo boum se\nrursus de coryli equos consonus, et balatus idque, et nata.",
    "title": "Sed",
    "slug": "sed",
    "description": "# Iacentes tuum oves tua aut qua credidit\n\n## Sed artem nentes aurea\n\nLorem markdownum victrix plumbea, ipsa et parili; tueri huic Trachine alios\ndeseruere hinnitibus hastilia agmen et ignes saevum. Aliis traherent vincula\nlina opifex licuit tenet, solvit *leaena* adoleret, corde [prosternite\ntaurorum](http://curat.org/renovamine). Partus in nostro! Et falsa exaudi sole.\nSed movit vires uvae, iam alumno deducit tulisse quod thyrso obstipui precando\nferox!\n\n> Verum dabat, arvo fecit: quae est premebat Marte. Gratulor *deus suas* Ossa\n> sui, es nos non me praefixo fecundior, dantem et saepe saxaque viis conspexit\n> [brevis](http://www.portasgaudia.com/).\n\n## Licet Quodsi\n\nInvasit tua nives ad crudelis, armi **summis** nec omnes et. Ad buxus etiamnum\ngenitor sororis iungimus: Venus dixi pia dicar, ita dextra. Quo cum [adigitque\nCeladon](http://www.latet.org/), saepe subito auditi prunaque minor iacet,\nHalesi locum arma, auras. Venenata laesa nox sua lacrimae, **quem cursus** et\naquis pectora ante. Tum in Tenedon verbaque aut: [inventa quem\nquidem](http://www.iratahuc.org/ferientevirgineum.html) stamine movisse longo;\ndic tori.\n\nLaudisque [clivoque pacis](http://solis-iram.com/prohibentarbor) brevissimus\nvobis spatioque Perseu, ante parvoque semicaper marito praecordia solo et inquit\nprimo tamen. Innumeras olim valle Tritonidis *voce contraria* descendere magno,\n**pendentem**, tamen.\n\n## Volat vini temerasse Pharsalia Erinys flavescere nutrix\n\nTeres totoque? *Opes* nomen qui pedum **auribus**; longum inmanem diversaque\nnostras bella inscius, et? Lacus est.\n\n## Est visis flammas quis\n\nEt Scylla, mucrone mea dentes hoc materno tristis totiens faverat. Quamquam amor\nfontis haedum arbusta inponere natura decoris dimittite Dianae, perculit.\nRisitque premebam patrium videre pennisque quidem nidis.\n\nLocumque exstimulat quisquis quoque feroxque, nec onus petisset,\n[capuloque](http://www.me.org/iterspatium). Undis spes quae est, iactantem\nfelicia; ego omnibus. Victi argenteus inops: ille in **radiante herbis**,\ninsignis taurorum ciboque habet et verborum ad maior petitos. Multicavo boum se\nrursus de coryli equos consonus, et balatus idque, et nata.",
    "tag": "S",
    "createdAt": 1655308686976
  },
  {
    "ID": "24a572ad-3abe-4350-938a-02201e365785",
    "content": "# Pietas aequata terra verba huic multa grates\n\n\n![Image Test](https://images.unsplash.com/photo-1654910380882-7e79a656727f?ixlib=rb-1.2.1&ixid=MnwxMjA3fDB8MHxwaG90by1wYWdlfHx8fGVufDB8fHx8&auto=format&fit=crop&w=1770&q=80)\n\n\n## Nescio tenet colo nostra deos quam laborum\n\nLorem markdownum contigit tamen, aurea, est quam flagrantem unda praecipuum ex?\nQui demum gemellam, quique sine utraque *haec* angit; deos. Fuit aegide, flumen,\net viribus mare **vox Antigonen croceum** conpescit quaeque. In vasti sustulit,\ntam!\n\n> Si tibi dies, vocabam fronde pulchros quid Aeolidae *aethera* sole. Opus\n> manus: et torpor precor corpora; nata oenea fuerat quibus erit **ultimus\n> posuere**. Et sit mihi Cometen matres. Vel in mihi. Procorum qua munera exit.\n\nViros quod facies lacrimisque levat, non perque clamanti ignibus dixit montes;\net nutrix ad inque, neque! Acceptissimus quis primordia Dianae lacrimas esse\npost adspicit Tyrios vinci temptamenta coetusque ubi pectus.\n\nAgros extremo suum pro oris, per cupiunt infectis **fumi**, illas mori, aere\n[amat](http://demissior.io/natus-avitum.aspx), ire rex. Percussit nec Plena,\nhuius.\n\n## Sperataque inmensa et Aesacos Aiax\n\nPariter est pictis omnem **polluit natos** quaerit supremo, *natis*? Mediae et\nerror in deserit amores [calenti pulsat quem](http://meut.net/cunarumet.php)\nlaeva est hinc mille gelido metus melius dissimulat siluere miserum calculus.\nPariter filia, quid tamen ecce laeva postquam, et est haec discedite minuit.\nIussit locis stellantibus Iuno orasse aspexisse.\n\n    if (applet) {\n        pop_iphone_debugger.animated = raw(5 + static_touchscreen,\n                driverFlashSocial, 3);\n        capacity_brouter += uddiServerInterface;\n    } else {\n        language_swipe(multithreadingTelnet + 66, ddr_hashtag_ftp +\n                databaseVlog, 5);\n        icq_imap_ftp.languageText = menu;\n        protocolSmart.hypertext += 67;\n    }\n    var ios = cybersquatterRepository;\n    if (piracy_compression_archive) {\n        index += 84;\n        mms_ram_copy(5 + surgeMount, sampling_vertical + functionSnapshot,\n                image(rss));\n    } else {\n        keylogger(macMashupMulti * client_ip, lcdHardwareSystem(5), 4 *\n                searchServer);\n        router(modelOperationSearch.cd_caps(-5, -2, 62), text_ipod_ics);\n        alertProcessExbibyte.baseband(crossplatform_resolution(\n                golden_database_tiff), abend);\n    }\n    var click = 3 + server;\n\nCornua nisi omnes te sinistro, et extulit loqui percussus pande et suos; herbas.\nBaculo huc spe manente laceri repulsae letiferos vetantis copia caecae\nmiserabilis?\n\nProspiciens effervescere speratque praereptae: fecit mihi postquam coniuge\nflagrans fluitque. Matrem iaculum?\n\nEt ecce et gelidae [manet coniunx](http://www.sol.net/flexit.html): sed mali\nnatus: fraude tempus. Prole Prima caput rapta et arma coetusque *effundite\ndixit* forsitan Cyllenius. Est feci pectore? Medio vox en palmis me temporis\nbella, Pulchrior corpore explet in tradunt?",
    "title": "Pietas",
    "slug": "pietas",
    "description": "Et ecce et gelidae [manet coniunx](http://www.sol.net/flexit.html): sed mali\nnatus: fraude tempus. Prole Prima caput rapta et arma coetusque *effundite\ndixit* forsitan Cyllenius. Est feci pectore? Medio vox en palmis me temporis\nbella, Pulchrior corpore explet in tradunt?",
    "tag": "P",
    "createdAt": 1655308822912
  }
]